kahi_wos_works/Kahi_wos_works.py
kahi_wos_works/__init__.py
kahi_wos_works/_version.py
Kahi_wos_works-0.1.3b0.dist-info/LICENSE
Kahi_wos_works-0.1.3b0.dist-info/METADATA
Kahi_wos_works-0.1.3b0.dist-info/WHEEL
Kahi_wos_works-0.1.3b0.dist-info/top_level.txt
Kahi_wos_works-0.1.3b0.dist-info/RECORD
