Metadata-Version: 2.1
Name: Kahi_wos_works
Version: 0.1.3b0
Summary: Kahi plugin to insert and update works from Web of Science
Home-page: https://github.com/colav/Kahi_plugins
Author: Colav
Author-email: colav@udea.edu.co
License: BSD
License-File: LICENSE
Requires-Dist: kahi
Requires-Dist: pymongo
Requires-Dist: joblib
Requires-Dist: thefuzz
Requires-Dist: kahi-impactu-utils
